LICENSE.txt
MANIFEST.in
README.rst
setup.cfg
setup.py
./py2jdbc/__init__.py
./py2jdbc/dbi.py
./py2jdbc/exc.py
./py2jdbc/jni.py
./py2jdbc/jvm.py
./py2jdbc/lang.py
./py2jdbc/math.py
./py2jdbc/mutf8.py
./py2jdbc/reflect.py
./py2jdbc/sig.py
./py2jdbc/sql.py
./py2jdbc/util.py
./py2jdbc/wrap.py
py2jdbc/__init__.py
py2jdbc/dbi.py
py2jdbc/exc.py
py2jdbc/jni.py
py2jdbc/jvm.py
py2jdbc/lang.py
py2jdbc/math.py
py2jdbc/mutf8.py
py2jdbc/reflect.py
py2jdbc/sig.py
py2jdbc/sql.py
py2jdbc/util.py
py2jdbc/wrap.py
py2jdbc.egg-info/PKG-INFO
py2jdbc.egg-info/SOURCES.txt
py2jdbc.egg-info/dependency_links.txt
py2jdbc.egg-info/top_level.txt
py2jdbc.egg-info/zip-safe
tests/__init__.py
tests/__init__.pyc
tests/config.py
tests/config.pyc
tests/derby.log
tests/test_cursor.py
tests/test_dbi.py
tests/test_derby.py
tests/test_jni.py
tests/test_jvm.py
tests/test_lang.py
tests/test_math.py
tests/test_mutf8.py
tests/test_mysql.py
tests/test_reflect.py
tests/test_sig.py
tests/test_sql.py
tests/test_util.py
tests/test_wrap.py