Metadata-Version: 1.1
Name: py2jdbc
Version: 0.0.5
Summary: Python DBI interface to JDBC databases
Home-page: https://github.com/swstephe/py2jdbc
Author: Scott Stephens
Author-email: scott@ariftek.com
License: BSD 2-Clause License
Keywords: Database,JDBC,JNI,PyPy
Platform: UNKNOWN
Classifier: Development Status :: 3 - Alpha
Classifier: Intended Audience :: Developers
Classifier: Intended Audience :: System Administrators
Classifier: License :: OSI Approved :: MIT License
Classifier: Programming Language :: Python
Classifier: Topic :: Database
